jucodecorrector/__init__.py
jucodecorrector/code_fixer_assistent.py
jucodecorrector-0.1.0.dist-info/LICENSE.txt
jucodecorrector-0.1.0.dist-info/METADATA
jucodecorrector-0.1.0.dist-info/WHEEL
jucodecorrector-0.1.0.dist-info/top_level.txt
jucodecorrector-0.1.0.dist-info/RECORD
