Metadata-Version: 2.1
Name: jucodecorrector
Version: 0.1.0
Summary: Python script to rivise error code based on the error messages using ChatGPT.
Home-page: https://github.com/isaacduong/jucodecorrector.git
Author: Isaac Duong
Author-email: isaaacduong@gmail.com
License: MIT
License-File: LICENSE.txt
Requires-Dist: ipywidgets (==8.0.6)
Requires-Dist: black (==23.3.0)
Requires-Dist: colored (==2.2.2)
Requires-Dist: ipython (==8.14.0)
Requires-Dist: openai (==0.27.8)
Requires-Dist: PyAutoGUI (==0.9.54)
Requires-Dist: Pygments (==2.15.1)
Requires-Dist: pyperclip (==1.8.2)
Requires-Dist: jupyter-ai-magics (==0.8.0)
